bar_graph_lib/__init__.py
bar_graph_lib/bar_plot.py
bar_graph_lib-0.0.1.dist-info/METADATA
bar_graph_lib-0.0.1.dist-info/WHEEL
bar_graph_lib-0.0.1.dist-info/top_level.txt
bar_graph_lib-0.0.1.dist-info/RECORD
