Metadata-Version: 2.4
Name: bar_graph_lib
Version: 0.0.1
Summary: This is a simple Python package for creating bar graph.
Home-page: 
Author: Hemanth kumar
Author-email: x22183744@student.ncirl.ie
License: MIT
Keywords: bar_graph_lib
Classifier: Intended Audience :: Education
Classifier: Operating System :: Microsoft :: Windows :: Windows 10
Classifier: Programming Language :: Python :: 3
Requires-Python: >=3.6
Dynamic: author
Dynamic: author-email
Dynamic: classifier
Dynamic: description
Dynamic: description-content-type
Dynamic: keywords
Dynamic: license
Dynamic: requires-python
Dynamic: summary
